dhv/__init__.py
dhv/__main__.py
dhv/commands/__init__.py
dhv/commands/disassembly.py
dhv/commands/main.py
dhv/data/__init__.py
dhv/data/config.py
dhv/data/locations.py
dhv/dhv.py
dhv/messages/__init__.py
dhv/messages/code_theme.py
dhv/messages/location.py
dhv/providers/__init__.py
dhv/providers/code_themes.py
dhv/providers/main.py
dhv/py.typed
dhv/python_docs.py
dhv/screens/__init__.py
dhv/screens/main.py
dhv/screens/opcode_counts.py
dhv/types.py
dhv/widgets/__init__.py
dhv/widgets/ast.py
dhv/widgets/disassembly.py
dhv/widgets/source.py
dhv-1.0.0.dist-info/WHEEL
dhv-1.0.0.dist-info/entry_points.txt
dhv-1.0.0.dist-info/METADATA
dhv-1.0.0.dist-info/RECORD
