Metadata-Version: 2.4
Name: dhv
Version: 1.0.0
Summary: A tool to dive into Python code
Keywords: terminal,tui,chui,documentation,python,bytecode,disassembly,disassembler
Author: Dave Pearson
Author-email: Dave Pearson <davep@davep.org>
License-Expression: GPL-3.0-or-later
Classifier: Development Status :: 5 - Production/Stable
Classifier: Environment :: Console
Classifier: Intended Audience :: Developers
Classifier: Intended Audience :: Information Technology
Classifier: Natural Language :: English
Classifier: Operating System :: OS Independent
Classifier: Programming Language :: Python :: 3 :: Only
Classifier: Programming Language :: Python :: 3.13
Classifier: Programming Language :: Python :: 3.14
Classifier: Programming Language :: Python :: 3.15
Classifier: Topic :: Documentation
Classifier: Topic :: Education
Classifier: Topic :: Software Development :: Disassemblers
Classifier: Topic :: Software Development :: Documentation
Classifier: Topic :: Software Development
Classifier: Topic :: Terminals
Classifier: Topic :: Utilities
Classifier: Typing :: Typed
Requires-Dist: textual[syntax]>=6.1.0
Requires-Dist: textual-enhanced>=0.13.0
Requires-Dist: textual-fspicker>=0.4.1
Requires-Dist: xdg-base-dirs>=6.0.2
Requires-Python: >=3.13
Project-URL: Discussions, https://github.com/davep/dhv/discussions
Project-URL: Documentation, https://dhv.davep.dev/
Project-URL: Homepage, https://dhv.davep.dev/
Project-URL: Issues, https://github.com/davep/dhv/issues
Project-URL: Repository, https://github.com/davep/dhv
Project-URL: Source, https://github.com/davep/dhv
